mpmq/__init__.py
mpmq/handler.py
mpmq/mpmq.py
mpmq-0.6.0.dist-info/METADATA
mpmq-0.6.0.dist-info/WHEEL
mpmq-0.6.0.dist-info/namespace_packages.txt
mpmq-0.6.0.dist-info/top_level.txt
mpmq-0.6.0.dist-info/zip-safe
mpmq-0.6.0.dist-info/RECORD
