Metadata-Version: 2.1
Name: mpmq
Version: 0.6.0
Summary: The mpmq module enables seamless interprocess communication between a parent and child processes when parallelizing a task across multiple workers.
Home-page: https://github.com/soda480/mpmq
Author: Emilio Reyes
Author-email: soda480@gmail.com
Maintainer: 
Maintainer-email: 
License: Apache License, Version 2.0
Classifier: Programming Language :: Python
Classifier: Programming Language :: Python :: 3.9
Classifier: Programming Language :: Python :: 3.10
Classifier: Programming Language :: Python :: 3.11
Classifier: Programming Language :: Python :: 3.12
